abundance_GaussF_esti/__init__.py
abundance_GaussF_esti/pipeline_abundance_GaussF_esti_loop.py
abundance_GaussF_esti-0.1.0.dist-info/LICENSE
abundance_GaussF_esti-0.1.0.dist-info/METADATA
abundance_GaussF_esti-0.1.0.dist-info/WHEEL
abundance_GaussF_esti-0.1.0.dist-info/entry_points.txt
abundance_GaussF_esti-0.1.0.dist-info/top_level.txt
abundance_GaussF_esti-0.1.0.dist-info/RECORD
